README.md
setup.py
mercado_bitcoin_api/__init__.py
mercado_bitcoin_api/api.py
mercado_bitcoin_api/market_stats.py
mercado_bitcoin_api/notifier.py
mercado_bitcoin_api.egg-info/PKG-INFO
mercado_bitcoin_api.egg-info/SOURCES.txt
mercado_bitcoin_api.egg-info/dependency_links.txt
mercado_bitcoin_api.egg-info/requires.txt
mercado_bitcoin_api.egg-info/top_level.txt