Metadata-Version: 2.1
Name: mercado-bitcoin-api
Version: 0.0.9
Summary: API implementation for Mercado Bitcoin (BR)
Home-page: https://github.com/pedrohml/mercado-bitcoin-api
Author: Pedro Lira
Author-email: pedrohml@gmail.com
License: UNKNOWN
Keywords: finance,bitcoin,api
Platform: UNKNOWN
Classifier: Development Status :: 3 - Alpha
Classifier: Intended Audience :: Developers
Classifier: Topic :: Software Development :: Build Tools
Classifier: License :: OSI Approved :: MIT License
Classifier: Programming Language :: Python :: 3.8
Classifier: Programming Language :: Python :: 3.7
Requires-Python: >=3.5, <4
Provides-Extra: dev
